{
  "packets":{
    "actorList":["0-730","0-731","0-732","0-733","274687-0","274688-0","274689-0"],
    "ai":[],
    "cellChangeFrom":[],
    "cellChangeTo":[],
    "container":["49989-0","49990-0","49991-0","49992-0","49993-0","49994-0","49995-0","49996-0","49997-0","49999-0","50000-0","50001-0","50002-0","50003-0","50004-0","50005-0","274691-0","475007-0","274687-0","274688-0","274689-0","0-730","0-731","0-732","0-733"],
    "death":[],
    "delete":[],
    "doorState":[],
    "equipment":["274687-0","274688-0","274689-0"],
    "lock":[],
    "place":[],
    "position":["274687-0","274688-0","274689-0","0-730","0-731","0-732","0-733"],
    "scale":[],
    "spawn":["0-730","0-731","0-732","0-733"],
    "state":[],
    "statsDynamic":["274687-0","274688-0","274689-0","0-730","0-731","0-732","0-733"],
    "trap":[],
    "clientScriptLocal":[],
    "miscellaneous":[],
    "spellsActive":[]
  },
  "entry":{
    "creationTime":1716740635,
    "description":"-8, 13"
  },
  "lastVisit":{
    "Fidgug":1716740782,
    "Benoit":1716740780
  },
  "recordLinks":[],
  "objectData":{
    "49993-0":{
      "refId":"flora_chokeweed_02",
      "inventory":[{
          "refId":"ingred_chokeweed_01",
          "count":1,
          "charge":-1,
          "enchantmentCharge":-1,
          "soul":""
        }]
    },
    "49994-0":{
      "refId":"flora_chokeweed_02",
      "inventory":[{
          "refId":"ingred_chokeweed_01",
          "count":1,
          "charge":-1,
          "enchantmentCharge":-1,
          "soul":""
        }]
    },
    "49995-0":{
      "refId":"flora_chokeweed_02",
      "inventory":[{
          "refId":"ingred_chokeweed_01",
          "count":1,
          "charge":-1,
          "enchantmentCharge":-1,
          "soul":""
        }]
    },
    "49996-0":{
      "refId":"flora_chokeweed_02",
      "inventory":[{
          "refId":"ingred_chokeweed_01",
          "count":1,
          "charge":-1,
          "enchantmentCharge":-1,
          "soul":""
        }]
    },
    "49997-0":{
      "refId":"flora_chokeweed_02",
      "inventory":[]
    },
    "49999-0":{
      "refId":"flora_chokeweed_02",
      "inventory":[{
          "refId":"ingred_chokeweed_01",
          "count":1,
          "charge":-1,
          "enchantmentCharge":-1,
          "soul":""
        }]
    },
    "50000-0":{
      "refId":"flora_chokeweed_02",
      "inventory":[{
          "refId":"ingred_chokeweed_01",
          "count":1,
          "charge":-1,
          "enchantmentCharge":-1,
          "soul":""
        }]
    },
    "50001-0":{
      "refId":"flora_chokeweed_02",
      "inventory":[{
          "refId":"ingred_chokeweed_01",
          "count":1,
          "charge":-1,
          "enchantmentCharge":-1,
          "soul":""
        }]
    },
    "50002-0":{
      "refId":"flora_chokeweed_02",
      "inventory":[{
          "refId":"ingred_chokeweed_01",
          "count":1,
          "charge":-1,
          "enchantmentCharge":-1,
          "soul":""
        }]
    },
    "50003-0":{
      "refId":"flora_chokeweed_02",
      "inventory":[{
          "refId":"ingred_chokeweed_01",
          "count":1,
          "charge":-1,
          "enchantmentCharge":-1,
          "soul":""
        }]
    },
    "50004-0":{
      "refId":"flora_chokeweed_02",
      "inventory":[{
          "refId":"ingred_chokeweed_01",
          "count":1,
          "charge":-1,
          "enchantmentCharge":-1,
          "soul":""
        }]
    },
    "50005-0":{
      "refId":"flora_chokeweed_02",
      "inventory":[{
          "refId":"ingred_chokeweed_01",
          "count":1,
          "charge":-1,
          "enchantmentCharge":-1,
          "soul":""
        }]
    },
    "274691-0":{
      "refId":"de_p_chest_02_gold_25",
      "inventory":[{
          "refId":"gold_001",
          "count":25,
          "charge":-1,
          "enchantmentCharge":-1,
          "soul":""
        }]
    },
    "475007-0":{
      "refId":"flora_kreshweed_01",
      "inventory":[]
    },
    "274687-0":{
      "refId":"shinammu radansour",
      "location":{
        "rotZ":2.6999995708466,
        "rotY":0,
        "posX":-64492.91015625,
        "posY":108102.9140625,
        "posZ":711.20971679688,
        "rotX":0
      },
      "stats":{
        "healthModified":50,
        "magickaModified":88,
        "fatigueModified":174,
        "healthBase":50,
        "healthCurrent":50,
        "magickaBase":88,
        "magickaCurrent":88,
        "fatigueBase":174,
        "fatigueCurrent":174
      },
      "equipment":{
        "7":{
          "refId":"chitin boots",
          "count":1,
          "charge":-1,
          "enchantmentCharge":-1
        },
        "8":{
          "refId":"common_shirt_01_u",
          "count":1,
          "charge":-1,
          "enchantmentCharge":-1
        },
        "10":{
          "refId":"expensive_skirt_01",
          "count":1,
          "charge":-1,
          "enchantmentCharge":-1
        },
        "16":{
          "refId":"chitin dagger",
          "count":1,
          "charge":-1,
          "enchantmentCharge":-1
        }
      },
      "inventory":[{
          "refId":"chitin boots",
          "count":1,
          "charge":-1,
          "enchantmentCharge":-1,
          "soul":""
        },{
          "refId":"expensive_skirt_01",
          "count":1,
          "charge":-1,
          "enchantmentCharge":-1,
          "soul":""
        },{
          "refId":"common_shirt_01_u",
          "count":1,
          "charge":-1,
          "enchantmentCharge":-1,
          "soul":""
        },{
          "refId":"common_shoes_01",
          "count":1,
          "charge":-1,
          "enchantmentCharge":-1,
          "soul":""
        },{
          "refId":"chitin dagger",
          "count":1,
          "charge":-1,
          "enchantmentCharge":-1,
          "soul":""
        }]
    },
    "274688-0":{
      "refId":"maeonius yentimilal",
      "location":{
        "rotZ":2.1999998092651,
        "rotY":0,
        "posX":-64575.85546875,
        "posY":107916.6953125,
        "posZ":705,
        "rotX":0
      },
      "stats":{
        "healthModified":75,
        "magickaModified":88,
        "fatigueModified":189,
        "healthBase":75,
        "healthCurrent":75,
        "magickaBase":88,
        "magickaCurrent":88,
        "fatigueBase":189,
        "fatigueCurrent":189
      },
      "equipment":{
        "1":{
          "refId":"netch_leather_boiled_cuirass",
          "count":1,
          "charge":-1,
          "enchantmentCharge":-1
        },
        "7":{
          "refId":"netch_leather_boots",
          "count":1,
          "charge":-1,
          "enchantmentCharge":-1
        },
        "8":{
          "refId":"common_shirt_02_h",
          "count":1,
          "charge":-1,
          "enchantmentCharge":-1
        },
        "9":{
          "refId":"common_pants_05",
          "count":1,
          "charge":-1,
          "enchantmentCharge":-1
        },
        "16":{
          "refId":"chitin club",
          "count":1,
          "charge":-1,
          "enchantmentCharge":-1
        }
      },
      "inventory":[{
          "refId":"netch_leather_boots",
          "count":1,
          "charge":-1,
          "enchantmentCharge":-1,
          "soul":""
        },{
          "refId":"netch_leather_boiled_cuirass",
          "count":1,
          "charge":-1,
          "enchantmentCharge":-1,
          "soul":""
        },{
          "refId":"common_shirt_02_h",
          "count":1,
          "charge":-1,
          "enchantmentCharge":-1,
          "soul":""
        },{
          "refId":"common_shoes_01",
          "count":1,
          "charge":-1,
          "enchantmentCharge":-1,
          "soul":""
        },{
          "refId":"common_pants_05",
          "count":1,
          "charge":-1,
          "enchantmentCharge":-1,
          "soul":""
        },{
          "refId":"chitin club",
          "count":1,
          "charge":-1,
          "enchantmentCharge":-1,
          "soul":""
        }]
    },
    "274689-0":{
      "refId":"pilun ashapaladdon",
      "location":{
        "rotZ":6.1831846237183,
        "rotY":0,
        "posX":-64429.7578125,
        "posY":107714.8828125,
        "posZ":705,
        "rotX":0
      },
      "stats":{
        "healthModified":88,
        "magickaModified":90,
        "fatigueModified":205,
        "healthBase":88,
        "healthCurrent":88,
        "magickaBase":90,
        "magickaCurrent":90,
        "fatigueBase":205,
        "fatigueCurrent":205
      },
      "equipment":{
        "1":{
          "refId":"netch_leather_boiled_cuirass",
          "count":1,
          "charge":-1,
          "enchantmentCharge":-1
        },
        "6":{
          "refId":"netch_leather_gauntlet_right",
          "count":1,
          "charge":-1,
          "enchantmentCharge":-1
        },
        "7":{
          "refId":"netch_leather_boots",
          "count":1,
          "charge":-1,
          "enchantmentCharge":-1
        },
        "9":{
          "refId":"common_pants_03_c",
          "count":1,
          "charge":-1,
          "enchantmentCharge":-1
        },
        "16":{
          "refId":"chitin spear",
          "count":1,
          "charge":-1,
          "enchantmentCharge":-1
        }
      },
      "inventory":[{
          "refId":"netch_leather_gauntlet_right",
          "count":1,
          "charge":-1,
          "enchantmentCharge":-1,
          "soul":""
        },{
          "refId":"netch_leather_boots",
          "count":1,
          "charge":-1,
          "enchantmentCharge":-1,
          "soul":""
        },{
          "refId":"netch_leather_boiled_cuirass",
          "count":1,
          "charge":-1,
          "enchantmentCharge":-1,
          "soul":""
        },{
          "refId":"common_shoes_01",
          "count":1,
          "charge":-1,
          "enchantmentCharge":-1,
          "soul":""
        },{
          "refId":"common_pants_03_c",
          "count":1,
          "charge":-1,
          "enchantmentCharge":-1,
          "soul":""
        },{
          "refId":"chitin spear",
          "count":1,
          "charge":-1,
          "enchantmentCharge":-1,
          "soul":""
        }]
    },
    "0-733":{
      "refId":"scrib",
      "location":{
        "rotZ":1.7812950611115,
        "rotY":0,
        "posX":-64041.71875,
        "posY":113974.4609375,
        "posZ":786.16815185547,
        "rotX":-0.34391364455223
      },
      "stats":{
        "healthModified":8,
        "magickaModified":12,
        "fatigueModified":300,
        "healthBase":8,
        "healthCurrent":8,
        "magickaBase":12,
        "magickaCurrent":12,
        "fatigueBase":300,
        "fatigueCurrent":300
      },
      "inventory":[]
    },
    "0-732":{
      "refId":"rat_blighted",
      "location":{
        "rotZ":-2.2051012516022,
        "rotY":0,
        "posX":-59413.6640625,
        "posY":114352.484375,
        "posZ":1648.1086425781,
        "rotX":-0.018772777169943
      },
      "stats":{
        "healthModified":45,
        "magickaModified":10,
        "fatigueModified":76,
        "healthBase":45,
        "healthCurrent":45,
        "magickaBase":10,
        "magickaCurrent":10,
        "fatigueBase":76,
        "fatigueCurrent":76
      },
      "inventory":[]
    },
    "0-731":{
      "refId":"scrib",
      "location":{
        "rotZ":2.0000002384186,
        "rotY":0,
        "posX":-59544.3203125,
        "posY":106750.3828125,
        "posZ":1196.4929199219,
        "rotX":0
      },
      "stats":{
        "healthModified":8,
        "magickaModified":12,
        "fatigueModified":300,
        "healthBase":8,
        "healthCurrent":8,
        "magickaBase":12,
        "magickaCurrent":12,
        "fatigueBase":300,
        "fatigueCurrent":300
      },
      "inventory":[]
    },
    "0-730":{
      "refId":"nix-hound",
      "location":{
        "rotZ":2.0000002384186,
        "rotY":0,
        "posX":-58787.390625,
        "posY":108214.2265625,
        "posZ":1104.447265625,
        "rotX":0
      },
      "stats":{
        "healthModified":23,
        "magickaModified":10,
        "fatigueModified":400,
        "healthBase":23,
        "healthCurrent":23,
        "magickaBase":10,
        "magickaCurrent":10,
        "fatigueBase":400,
        "fatigueCurrent":400
      },
      "inventory":[{
          "refId":"ingred_hound_meat_01",
          "count":1,
          "charge":-1,
          "enchantmentCharge":-1,
          "soul":""
        }]
    },
    "49989-0":{
      "refId":"flora_chokeweed_02",
      "inventory":[{
          "refId":"ingred_chokeweed_01",
          "count":1,
          "charge":-1,
          "enchantmentCharge":-1,
          "soul":""
        }]
    },
    "49990-0":{
      "refId":"flora_chokeweed_02",
      "inventory":[{
          "refId":"ingred_chokeweed_01",
          "count":1,
          "charge":-1,
          "enchantmentCharge":-1,
          "soul":""
        }]
    },
    "49991-0":{
      "refId":"flora_chokeweed_02",
      "inventory":[{
          "refId":"ingred_chokeweed_01",
          "count":1,
          "charge":-1,
          "enchantmentCharge":-1,
          "soul":""
        }]
    },
    "49992-0":{
      "refId":"flora_chokeweed_02",
      "inventory":[{
          "refId":"ingred_chokeweed_01",
          "count":1,
          "charge":-1,
          "enchantmentCharge":-1,
          "soul":""
        }]
    }
  },
  "loadState":{
    "hasFullContainerData":true,
    "hasFullActorList":true
  }
}