{
  "packets":{
    "actorList":["0-177"],
    "ai":[],
    "cellChangeFrom":[],
    "cellChangeTo":[],
    "container":["0-177"],
    "death":[],
    "delete":[],
    "doorState":[],
    "equipment":[],
    "lock":[],
    "place":[],
    "position":["0-177"],
    "scale":[],
    "spawn":["0-177"],
    "state":[],
    "statsDynamic":["0-177"],
    "trap":[],
    "miscellaneous":[],
    "clientScriptLocal":[],
    "spellsActive":[]
  },
  "entry":{
    "description":"0, 1",
    "creationTime":1715975431
  },
  "lastVisit":[],
  "recordLinks":[],
  "objectData":{
    "0-177":{
      "refId":"cliff racer",
      "location":{
        "posX":1.1853492259979,
        "posY":15721.423828125,
        "posZ":3133.052734375,
        "rotX":0,
        "rotZ":2.3004648685455,
        "rotY":0
      },
      "stats":{
        "healthBase":45,
        "healthCurrent":45,
        "magickaBase":20,
        "magickaCurrent":20,
        "fatigueBase":400,
        "fatigueCurrent":400,
        "healthModified":45,
        "magickaModified":20,
        "fatigueModified":400
      },
      "inventory":[]
    }
  },
  "loadState":{
    "hasFullContainerData":false,
    "hasFullActorList":false
  }
}