{
  "packets":{
    "actorList":["0-965","0-966","0-967","0-968","0-969","0-970","0-954"],
    "ai":[],
    "cellChangeFrom":[],
    "cellChangeTo":[],
    "container":["283811-0","283822-0","283846-0","318848-0","325168-0","325169-0","325170-0","325171-0","325172-0","325173-0","325174-0","325175-0","325176-0","325182-0","325183-0","325194-0","0-965","0-966","0-967","0-968","0-969","0-970","0-954"],
    "death":[],
    "delete":[],
    "doorState":[],
    "equipment":[],
    "lock":[],
    "place":[],
    "position":["0-965","0-966","0-967","0-968","0-969","0-970","0-954"],
    "scale":[],
    "spawn":["0-965","0-966","0-967","0-968","0-969","0-970","0-954"],
    "state":[],
    "statsDynamic":["0-965","0-966","0-967","0-968","0-969","0-970","0-954"],
    "trap":[],
    "clientScriptLocal":[],
    "spellsActive":[],
    "miscellaneous":[]
  },
  "entry":{
    "description":"2, 21",
    "creationTime":1717186843
  },
  "lastVisit":{
    "Fidgug":1717187141,
    "Benoit":1717187105
  },
  "recordLinks":[],
  "objectData":{
    "325170-0":{
      "refId":"flora_green_lichen_01",
      "inventory":[{
          "refId":"ingred_green_lichen_01",
          "count":1,
          "charge":-1,
          "enchantmentCharge":-1,
          "soul":""
        }]
    },
    "325171-0":{
      "refId":"flora_green_lichen_02",
      "inventory":[{
          "refId":"ingred_green_lichen_01",
          "count":1,
          "charge":-1,
          "enchantmentCharge":-1,
          "soul":""
        }]
    },
    "325172-0":{
      "refId":"flora_kreshweed_01",
      "inventory":[{
          "refId":"ingred_kresh_fiber_01",
          "count":1,
          "charge":-1,
          "enchantmentCharge":-1,
          "soul":""
        }]
    },
    "325173-0":{
      "refId":"flora_stoneflower_01",
      "inventory":[{
          "refId":"ingred_stoneflower_petals_01",
          "count":1,
          "charge":-1,
          "enchantmentCharge":-1,
          "soul":""
        }]
    },
    "325174-0":{
      "refId":"flora_willow_flower_01",
      "inventory":[{
          "refId":"ingred_willow_anther_01",
          "count":1,
          "charge":-1,
          "enchantmentCharge":-1,
          "soul":""
        }]
    },
    "0-968":{
      "refId":"cliff racer",
      "location":{
        "posX":22808.279296875,
        "posY":174640.703125,
        "posZ":1819.6225585938,
        "rotX":0.0019130725413561,
        "rotZ":0.27706956863403,
        "rotY":0
      },
      "stats":{
        "magickaCurrent":20,
        "fatigueBase":400,
        "fatigueCurrent":400,
        "fatigueModified":400,
        "magickaBase":20,
        "healthModified":45,
        "healthBase":45,
        "healthCurrent":45,
        "magickaModified":20
      },
      "inventory":[{
          "refId":"ingred_racer_plumes_01",
          "count":1,
          "charge":-1,
          "enchantmentCharge":-1,
          "soul":""
        }]
    },
    "325175-0":{
      "refId":"flora_willow_flower_02",
      "inventory":[{
          "refId":"ingred_willow_anther_01",
          "count":1,
          "charge":-1,
          "enchantmentCharge":-1,
          "soul":""
        }]
    },
    "325176-0":{
      "refId":"flora_kreshweed_02",
      "inventory":[]
    },
    "325182-0":{
      "refId":"flora_kreshweed_03",
      "inventory":[{
          "refId":"ingred_kresh_fiber_01",
          "count":1,
          "charge":-1,
          "enchantmentCharge":-1,
          "soul":""
        }]
    },
    "325183-0":{
      "refId":"flora_kreshweed_01",
      "inventory":[{
          "refId":"ingred_kresh_fiber_01",
          "count":1,
          "charge":-1,
          "enchantmentCharge":-1,
          "soul":""
        }]
    },
    "325194-0":{
      "refId":"flora_kreshweed_02",
      "inventory":[{
          "refId":"ingred_kresh_fiber_01",
          "count":1,
          "charge":-1,
          "enchantmentCharge":-1,
          "soul":""
        }]
    },
    "0-970":{
      "refId":"cliff racer",
      "location":{
        "posX":17429.681640625,
        "posY":178478.84375,
        "posZ":939.07080078125,
        "rotX":0.0066547431051731,
        "rotZ":-2.8700006008148,
        "rotY":0
      },
      "stats":{
        "magickaCurrent":20,
        "fatigueBase":400,
        "fatigueCurrent":400,
        "fatigueModified":400,
        "magickaBase":20,
        "healthModified":45,
        "healthBase":45,
        "healthCurrent":45,
        "magickaModified":20
      },
      "inventory":[{
          "refId":"ingred_racer_plumes_01",
          "count":1,
          "charge":-1,
          "enchantmentCharge":-1,
          "soul":""
        }]
    },
    "0-969":{
      "refId":"scrib",
      "location":{
        "posX":19639.525390625,
        "posY":177654.65625,
        "posZ":833.38629150391,
        "rotX":0,
        "rotZ":0,
        "rotY":0
      },
      "stats":{
        "magickaCurrent":12,
        "fatigueBase":300,
        "fatigueCurrent":300,
        "fatigueModified":300,
        "magickaBase":12,
        "healthModified":8,
        "healthBase":8,
        "healthCurrent":8,
        "magickaModified":12
      },
      "inventory":[]
    },
    "0-967":{
      "refId":"mudcrab-diseased",
      "location":{
        "posX":23171.0546875,
        "posY":172984.171875,
        "posZ":151.46450805664,
        "rotX":0,
        "rotZ":0,
        "rotY":0
      },
      "stats":{
        "magickaCurrent":5,
        "fatigueBase":25,
        "fatigueCurrent":25,
        "fatigueModified":25,
        "magickaBase":5,
        "healthModified":15,
        "healthBase":15,
        "healthCurrent":15,
        "magickaModified":5
      },
      "inventory":[{
          "refId":"ingred_crab_meat_01",
          "count":2,
          "charge":-1,
          "enchantmentCharge":-1,
          "soul":""
        }]
    },
    "0-966":{
      "refId":"cliff racer",
      "location":{
        "posX":22219.103515625,
        "posY":172736.25,
        "posZ":187.82162475586,
        "rotX":-0.004863103851676,
        "rotZ":-1.7148540019989,
        "rotY":0
      },
      "stats":{
        "magickaCurrent":20,
        "fatigueBase":400,
        "fatigueCurrent":400,
        "fatigueModified":400,
        "magickaBase":20,
        "healthModified":45,
        "healthBase":45,
        "healthCurrent":45,
        "magickaModified":20
      },
      "inventory":[]
    },
    "0-965":{
      "refId":"scamp",
      "location":{
        "posX":24027.0546875,
        "posY":176127.578125,
        "posZ":746.08551025391,
        "rotX":0,
        "rotZ":0,
        "rotY":0
      },
      "stats":{
        "magickaCurrent":100,
        "fatigueBase":400,
        "fatigueCurrent":400,
        "fatigueModified":400,
        "magickaBase":100,
        "healthModified":45,
        "healthBase":45,
        "healthCurrent":45,
        "magickaModified":100
      },
      "inventory":[]
    },
    "325169-0":{
      "refId":"flora_gold_kanet_01",
      "inventory":[{
          "refId":"ingred_gold_kanet_01",
          "count":1,
          "charge":-1,
          "enchantmentCharge":-1,
          "soul":""
        }]
    },
    "283811-0":{
      "refId":"flora_kreshweed_01",
      "inventory":[{
          "refId":"ingred_kresh_fiber_01",
          "count":1,
          "charge":-1,
          "enchantmentCharge":-1,
          "soul":""
        }]
    },
    "283822-0":{
      "refId":"flora_kreshweed_01",
      "inventory":[]
    },
    "283846-0":{
      "refId":"flora_kreshweed_01",
      "inventory":[{
          "refId":"ingred_kresh_fiber_01",
          "count":1,
          "charge":-1,
          "enchantmentCharge":-1,
          "soul":""
        }]
    },
    "318848-0":{
      "refId":"flora_kreshweed_01",
      "inventory":[{
          "refId":"ingred_kresh_fiber_01",
          "count":1,
          "charge":-1,
          "enchantmentCharge":-1,
          "soul":""
        }]
    },
    "325168-0":{
      "refId":"flora_black_anther_01",
      "inventory":[{
          "refId":"ingred_black_anther_01",
          "count":1,
          "charge":-1,
          "enchantmentCharge":-1,
          "soul":""
        }]
    },
    "0-954":{
      "refId":"slaughterfish",
      "location":{
        "posX":17225.822265625,
        "posY":180167.265625,
        "posZ":-303.66275024414,
        "rotX":0,
        "rotZ":0.94721293449402,
        "rotY":0
      },
      "stats":{
        "magickaCurrent":10,
        "fatigueBase":400,
        "fatigueCurrent":399.99417114258,
        "fatigueModified":400,
        "magickaBase":10,
        "healthModified":23,
        "healthBase":23,
        "healthCurrent":23,
        "magickaModified":10
      },
      "inventory":[{
          "refId":"ingred_scales_01",
          "count":2,
          "charge":-1,
          "enchantmentCharge":-1,
          "soul":""
        }]
    }
  },
  "loadState":{
    "hasFullActorList":true,
    "hasFullContainerData":true
  }
}