{
  "packets":{
    "actorList":[],
    "ai":[],
    "cellChangeFrom":[],
    "cellChangeTo":[],
    "container":[],
    "death":[],
    "delete":[],
    "doorState":[],
    "equipment":[],
    "lock":[],
    "place":[],
    "position":[],
    "scale":[],
    "spawn":[],
    "state":["113442-0"],
    "statsDynamic":[],
    "trap":[],
    "clientScriptLocal":[],
    "spellsActive":[],
    "miscellaneous":[]
  },
  "entry":{
    "description":"Gnaar Mok, Nadene Rotheran's Shack",
    "creationTime":1713904668
  },
  "lastVisit":[],
  "recordLinks":[],
  "objectData":{
    "113442-0":{
      "refId":"daren adryn",
      "state":false
    }
  },
  "loadState":{
    "hasFullActorList":false,
    "hasFullContainerData":false
  }
}